dj_media_url.py
dj_media_url-0.3.dist-info/DESCRIPTION.rst
dj_media_url-0.3.dist-info/METADATA
dj_media_url-0.3.dist-info/RECORD
dj_media_url-0.3.dist-info/WHEEL
dj_media_url-0.3.dist-info/metadata.json
dj_media_url-0.3.dist-info/top_level.txt
